setup.py
switchDiscovery/__init__.py
switchDiscovery/logger.py
switchDiscovery/switchDiscovery.py
switchDiscovery.egg-info/PKG-INFO
switchDiscovery.egg-info/SOURCES.txt
switchDiscovery.egg-info/dependency_links.txt
switchDiscovery.egg-info/requires.txt
switchDiscovery.egg-info/top_level.txt
switchDiscovery.egg-info/zip-safe