Metadata-Version: 1.1
Name: switchDiscovery
Version: 1.2.2.dev1
Summary: CISCO Switch Devices Discovery tool
Home-page: https://github.com/roshan3133/switchDiscovery
Author: Aniket Gole
Author-email: roshan3133@gmail.com
License: MIT
Keywords: Cisco Switch information Discovery
Platform: UNKNOWN
Classifier: Development Status :: 3 - Alpha
Classifier: Programming Language :: Python :: 2.7
Classifier: Programming Language :: Python :: 3.4
